<?xml version="1.0" encoding="utf-8" ?>
<dwsync>
<file name="evesham189settings.css" server="185.53.173.97/public_html/" local="131353463020000000" remote="131377569000000000" Dst="2" />
<file name="evesham189styles.css" server="185.53.173.97/public_html/" local="131353462680000000" remote="131377569000000000" Dst="2" />
<file name="styles.css" server="185.53.173.97/public_html/" local="131352495300000000" remote="131377569000000000" Dst="2" />
<file name="styles.php" server="185.53.173.97/public_html/" local="131357687140000000" remote="131377569000000000" Dst="2" />
<file name="composer.css" server="185.53.173.97/public_html/" local="131378425492797012" remote="131378425800000000" Dst="2" />
<file name="external.css" server="185.53.173.97/public_html/" local="131381881993725389" remote="131378534400000000" Dst="2" />
<file name="custom.css" server="185.53.173.97/public_html/" local="131378428692276872" remote="131378428800000000" Dst="2" />
<file name="responsive.css" server="185.53.173.97/public_html/" local="131381882005747119" remote="131378500200000000" Dst="2" />
<file name="seo.css" server="185.53.173.97/public_html/" local="131378439740925194" remote="131378439600000000" Dst="2" />
</dwsync>